atarashi/__init__.py
atarashi/atarashii.py
atarashi/build_deps.py
atarashi/imtihaan.py
atarashi/agents/__init__.py
atarashi/agents/atarashiAgent.py
atarashi/agents/cosineSimNgram.py
atarashi/agents/dameruLevenDist.py
atarashi/agents/tfidf.py
atarashi/agents/wordFrequencySimilarity.py
atarashi/data/Ngram_keywords.json
atarashi/data/licenses/processedLicenses.csv
atarashi/libs/__init__.py
atarashi/libs/commentPreprocessor.py
atarashi/libs/initialmatch.py
atarashi/libs/license_clustering.py
atarashi/libs/ngram.py
atarashi/libs/utils.py
atarashi/license/__init__.py
atarashi/license/licenseDownloader.py
atarashi/license/licenseLoader.py
atarashi/license/licensePreprocessor.py
atarashi/license/license_merger.py
atarashi-0.0.11.dist-info/LICENSE
atarashi-0.0.11.dist-info/METADATA
atarashi-0.0.11.dist-info/WHEEL
atarashi-0.0.11.dist-info/entry_points.txt
atarashi-0.0.11.dist-info/top_level.txt
atarashi-0.0.11.dist-info/RECORD
