Metadata-Version: 2.1
Name: atarashi
Version: 0.0.11
Summary: An intelligent license scanner.
Home-page: https://github.com/fossology/atarashi
Author: Aman Jain
Author-email: amanjain5221@gmail.com
License: GPL-2.0-only
Keywords: atarashi,license,license-scanner,oss,oss-compliance
Platform: UNKNOWN
Classifier: Development Status :: 2 - Pre-Alpha
Classifier: Topic :: Utilities
Classifier: Intended Audience :: Legal Industry
Classifier: License :: OSI Approved :: GNU General Public License v2 (GPLv2)
Requires-Python: >=3.5
Requires-Dist: nirjas (>=0.0.3)
Requires-Dist: numpy (>=1.16.0)
Requires-Dist: pandas (>=0.23.1)
Requires-Dist: pyxDamerauLevenshtein (>=1.5)
Requires-Dist: scikit-learn (>=0.18.1)
Requires-Dist: scipy (>=0.18.1)
Requires-Dist: setuptools (>=39.2.0)
Requires-Dist: textdistance (>=3.0.3)
Requires-Dist: tqdm (>=4.23.4)
Requires-Dist: urllib3 (>=1.24.1)
